darwinex_client/__init__.py
darwinex_client/client.py
darwinex_client-0.1.0.dist-info/DESCRIPTION.rst
darwinex_client-0.1.0.dist-info/METADATA
darwinex_client-0.1.0.dist-info/RECORD
darwinex_client-0.1.0.dist-info/WHEEL
darwinex_client-0.1.0.dist-info/metadata.json
darwinex_client-0.1.0.dist-info/top_level.txt
