Metadata-Version: 2.0
Name: darwinex-client
Version: 0.1.0
Summary: Darwinex API client
Home-page: https://github.com/noviluni/darwinex
Author: Marc Hernandez
Author-email: noviluni@gmail.com
License: MIT
Project-URL: Source, https://github.com/noviluni/darwinex
Project-URL: Bug Reports, https://github.com/noviluni/darwinex/issues
Keywords: darwinex darwinex-api darwinex-client trading api-client
Platform: UNKNOWN
Classifier: Development Status :: 3 - Alpha
Classifier: License :: OSI Approved :: MIT License
Classifier: Programming Language :: Python :: 3
Classifier: Programming Language :: Python :: 3.4
Classifier: Programming Language :: Python :: 3.5
Classifier: Programming Language :: Python :: 3.6
Requires-Dist: requests
